<?xml version="1.0" encoding="UTF-8"?>


<!DOCTYPE publicwhip
[
<!ENTITY ndash   "&#8211;">
<!ENTITY mdash   "&#8212;">
<!ENTITY iexcl   "&#161;">
<!ENTITY divide  "&#247;">
<!ENTITY euro    "&#8364;">
<!ENTITY trade   "&#8482;">
<!ENTITY bull    "&#8226;">
<!ENTITY lsquo   "&#8216;">
<!ENTITY rsquo   "&#8217;">
<!ENTITY sbquo   "&#8218;">
<!ENTITY ldquo   "&#8220;">
<!ENTITY rdquo   "&#8221;">
<!ENTITY bdquo   "&#8222;">
<!ENTITY dagger  "&#8224;">

<!ENTITY Ouml   "&#214;" >
<!ENTITY szlig  "&#223;" >
<!ENTITY agrave "&#224;" >
<!ENTITY aacute "&#225;" >
<!ENTITY acirc  "&#226;" >
<!ENTITY atilde "&#227;" >
<!ENTITY auml   "&#228;" >
<!ENTITY ccedil "&#231;" >
<!ENTITY egrave "&#232;" >
<!ENTITY eacute "&#233;" >
<!ENTITY ecirc  "&#234;" >
<!ENTITY euml   "&#235;" >
<!ENTITY iacute "&#237;" >
<!ENTITY icirc  "&#238;" >
<!ENTITY iuml	"&#239;" >
<!ENTITY ntilde "&#241;" >
<!ENTITY nbsp   "&#160;" >
<!ENTITY oacute "&#243;" >
<!ENTITY ocirc  "&#244;" >
<!ENTITY ouml   "&#246;" >
<!ENTITY oslash "&#248;" >
<!ENTITY uacute "&#250;" >
<!ENTITY uuml   "&#252;" >
<!ENTITY thorn  "&#254;" >

<!ENTITY pound  "&#163;" >
<!ENTITY sect   "&#167;" >
<!ENTITY copy   "&#169;" >
<!ENTITY reg    "&#174;" >
<!ENTITY deg    "&#176;" >
<!ENTITY plusmn "&#177;" >
<!ENTITY sup2   "&#178;" >
<!ENTITY micro  "&#181;" >
<!ENTITY para   "&#182;" >
<!ENTITY middot "&#183;" >
<!ENTITY ordm   "&#186;" >
<!ENTITY frac14 "&#188;" >
<!ENTITY frac12 "&#189;" >
<!ENTITY frac34 "&#190;" >
<!ENTITY oelig "&#339;" >
<!ENTITY aelig  "&#230;" >

]>

<publicwhip scrapeversion="/home/twfy-live/parldata/scrapedxml/lordspages/daylord2022-02-10b.xml" latest="no">
<gidredirect oldgid="uk.org.publicwhip/lords/2022-02-10b.1809.0" newgid="uk.org.publicwhip/lords/2022-02-10c.1809.0" matchtype="perfectmatch"/>
<gidredirect oldgid="uk.org.publicwhip/lords/2022-02-10b.1809.1" newgid="uk.org.publicwhip/lords/2022-02-10c.1809.1" matchtype="perfectmatch"/>
<gidredirect oldgid="uk.org.publicwhip/lords/2022-02-10b.1809.2" newgid="uk.org.publicwhip/lords/2022-02-10c.1809.2" matchtype="perfectmatch"/>
<gidredirect oldgid="uk.org.publicwhip/lords/2022-02-10b.1809.3" newgid="uk.org.publicwhip/lords/2022-02-10c.1809.3" matchtype="perfectmatch"/>
<gidredirect oldgid="uk.org.publicwhip/lords/2022-02-10b.1809.4" newgid="uk.org.publicwhip/lords/2022-02-10c.1809.4" matchtype="perfectmatch"/>
<gidredirect oldgid="uk.org.publicwhip/lords/2022-02-10b.1809.5" newgid="uk.org.publicwhip/lords/2022-02-10c.1809.5" matchtype="perfectmatch"/>
<gidredirect oldgid="uk.org.publicwhip/lords/2022-02-10b.1809.6" newgid="uk.org.publicwhip/lords/2022-02-10c.1809.6" matchtype="perfectmatch"/>
<gidredirect oldgid="uk.org.publicwhip/lords/2022-02-10b.1810.0" newgid="uk.org.publicwhip/lords/2022-02-10c.1810.0" matchtype="perfectmatch"/>
<gidredirect oldgid="uk.org.publicwhip/lords/2022-02-10b.1810.1" newgid="uk.org.publicwhip/lords/2022-02-10c.1810.1" matchtype="perfectmatch"/>
<gidredirect oldgid="uk.org.publicwhip/lords/2022-02-10b.1810.2" newgid="uk.org.publicwhip/lords/2022-02-10c.1810.2" matchtype="perfectmatch"/>
<gidredirect oldgid="uk.org.publicwhip/lords/2022-02-10b.1810.3" newgid="uk.org.publicwhip/lords/2022-02-10c.1810.3" matchtype="perfectmatch"/>
<gidredirect oldgid="uk.org.publicwhip/lords/2022-02-10b.1810.4" newgid="uk.org.publicwhip/lords/2022-02-10c.1810.4" matchtype="perfectmatch"/>
<gidredirect oldgid="uk.org.publicwhip/lords/2022-02-10b.1810.5" newgid="uk.org.publicwhip/lords/2022-02-10c.1810.5" matchtype="perfectmatch"/>
<gidredirect oldgid="uk.org.publicwhip/lords/2022-02-10b.1810.6" newgid="uk.org.publicwhip/lords/2022-02-10c.1810.6" matchtype="perfectmatch"/>
<gidredirect oldgid="uk.org.publicwhip/lords/2022-02-10b.1811.0" newgid="uk.org.publicwhip/lords/2022-02-10c.1811.0" matchtype="perfectmatch"/>
<gidredirect oldgid="uk.org.publicwhip/lords/2022-02-10b.1811.1" newgid="uk.org.publicwhip/lords/2022-02-10c.1811.1" matchtype="perfectmatch"/>
<gidredirect oldgid="uk.org.publicwhip/lords/2022-02-10b.1811.2" newgid="uk.org.publicwhip/lords/2022-02-10c.1811.2" matchtype="perfectmatch"/>
<gidredirect oldgid="uk.org.publicwhip/lords/2022-02-10b.1811.3" newgid="uk.org.publicwhip/lords/2022-02-10c.1811.3" matchtype="perfectmatch"/>
<gidredirect oldgid="uk.org.publicwhip/lords/2022-02-10b.1811.4" newgid="uk.org.publicwhip/lords/2022-02-10c.1811.4" matchtype="perfectmatch"/>
<gidredirect oldgid="uk.org.publicwhip/lords/2022-02-10b.1811.5" newgid="uk.org.publicwhip/lords/2022-02-10c.1811.5" matchtype="perfectmatch"/>
<gidredirect oldgid="uk.org.publicwhip/lords/2022-02-10b.1811.6" newgid="uk.org.publicwhip/lords/2022-02-10c.1811.6" matchtype="perfectmatch"/>
<gidredirect oldgid="uk.org.publicwhip/lords/2022-02-10b.1811.7" newgid="uk.org.publicwhip/lords/2022-02-10c.1811.7" matchtype="perfectmatch"/>
<gidredirect oldgid="uk.org.publicwhip/lords/2022-02-10b.1812.0" newgid="uk.org.publicwhip/lords/2022-02-10c.1812.0" matchtype="perfectmatch"/>
<gidredirect oldgid="uk.org.publicwhip/lords/2022-02-10b.1812.1" newgid="uk.org.publicwhip/lords/2022-02-10c.1812.1" matchtype="perfectmatch"/>
<gidredirect oldgid="uk.org.publicwhip/lords/2022-02-10b.1812.2" newgid="uk.org.publicwhip/lords/2022-02-10c.1812.2" matchtype="perfectmatch"/>
<gidredirect oldgid="uk.org.publicwhip/lords/2022-02-10b.1812.3" newgid="uk.org.publicwhip/lords/2022-02-10c.1812.3" matchtype="perfectmatch"/>
<gidredirect oldgid="uk.org.publicwhip/lords/2022-02-10b.1812.4" newgid="uk.org.publicwhip/lords/2022-02-10c.1812.4" matchtype="perfectmatch"/>
<gidredirect oldgid="uk.org.publicwhip/lords/2022-02-10b.1812.5" newgid="uk.org.publicwhip/lords/2022-02-10c.1812.5" matchtype="perfectmatch"/>
<gidredirect oldgid="uk.org.publicwhip/lords/2022-02-10b.1812.6" newgid="uk.org.publicwhip/lords/2022-02-10c.1812.6" matchtype="perfectmatch"/>
<gidredirect oldgid="uk.org.publicwhip/lords/2022-02-10b.1812.7" newgid="uk.org.publicwhip/lords/2022-02-10c.1812.7" matchtype="perfectmatch"/>
<gidredirect oldgid="uk.org.publicwhip/lords/2022-02-10b.1813.0" newgid="uk.org.publicwhip/lords/2022-02-10c.1813.0" matchtype="perfectmatch"/>
<gidredirect oldgid="uk.org.publicwhip/lords/2022-02-10b.1813.1" newgid="uk.org.publicwhip/lords/2022-02-10c.1813.1" matchtype="perfectmatch"/>
<gidredirect oldgid="uk.org.publicwhip/lords/2022-02-10b.1813.2" newgid="uk.org.publicwhip/lords/2022-02-10c.1813.2" matchtype="perfectmatch"/>
<gidredirect oldgid="uk.org.publicwhip/lords/2022-02-10b.1813.3" newgid="uk.org.publicwhip/lords/2022-02-10c.1813.3" matchtype="perfectmatch"/>
<gidredirect oldgid="uk.org.publicwhip/lords/2022-02-10b.1813.4" newgid="uk.org.publicwhip/lords/2022-02-10c.1813.4" matchtype="perfectmatch"/>
<gidredirect oldgid="uk.org.publicwhip/lords/2022-02-10b.1813.5" newgid="uk.org.publicwhip/lords/2022-02-10c.1813.5" matchtype="perfectmatch"/>
<gidredirect oldgid="uk.org.publicwhip/lords/2022-02-10b.1813.6" newgid="uk.org.publicwhip/lords/2022-02-10c.1813.6" matchtype="perfectmatch"/>
<gidredirect oldgid="uk.org.publicwhip/lords/2022-02-10b.1814.0" newgid="uk.org.publicwhip/lords/2022-02-10c.1814.0" matchtype="perfectmatch"/>
<gidredirect oldgid="uk.org.publicwhip/lords/2022-02-10b.1814.1" newgid="uk.org.publicwhip/lords/2022-02-10c.1814.1" matchtype="perfectmatch"/>
<gidredirect oldgid="uk.org.publicwhip/lords/2022-02-10b.1814.2" newgid="uk.org.publicwhip/lords/2022-02-10c.1814.2" matchtype="perfectmatch"/>
<gidredirect oldgid="uk.org.publicwhip/lords/2022-02-10b.1814.3" newgid="uk.org.publicwhip/lords/2022-02-10c.1814.3" matchtype="perfectmatch"/>
<gidredirect oldgid="uk.org.publicwhip/lords/2022-02-10b.1814.4" newgid="uk.org.publicwhip/lords/2022-02-10c.1814.4" matchtype="perfectmatch"/>
<gidredirect oldgid="uk.org.publicwhip/lords/2022-02-10b.1814.5" newgid="uk.org.publicwhip/lords/2022-02-10c.1814.5" matchtype="perfectmatch"/>
<gidredirect oldgid="uk.org.publicwhip/lords/2022-02-10b.1815.0" newgid="uk.org.publicwhip/lords/2022-02-10c.1815.0" matchtype="perfectmatch"/>
<gidredirect oldgid="uk.org.publicwhip/lords/2022-02-10b.1815.1" newgid="uk.org.publicwhip/lords/2022-02-10c.1815.1" matchtype="perfectmatch"/>
<gidredirect oldgid="uk.org.publicwhip/lords/2022-02-10b.1815.2" newgid="uk.org.publicwhip/lords/2022-02-10c.1815.2" matchtype="perfectmatch"/>
<gidredirect oldgid="uk.org.publicwhip/lords/2022-02-10b.1815.3" newgid="uk.org.publicwhip/lords/2022-02-10c.1815.3" matchtype="perfectmatch"/>
<gidredirect oldgid="uk.org.publicwhip/lords/2022-02-10b.1815.4" newgid="uk.org.publicwhip/lords/2022-02-10c.1815.4" matchtype="perfectmatch"/>
<gidredirect oldgid="uk.org.publicwhip/lords/2022-02-10b.1816.0" newgid="uk.org.publicwhip/lords/2022-02-10c.1816.0" matchtype="perfectmatch"/>
<gidredirect oldgid="uk.org.publicwhip/lords/2022-02-10b.1816.1" newgid="uk.org.publicwhip/lords/2022-02-10c.1816.1" matchtype="perfectmatch"/>
<gidredirect oldgid="uk.org.publicwhip/lords/2022-02-10b.1816.2" newgid="uk.org.publicwhip/lords/2022-02-10c.1816.2" matchtype="perfectmatch"/>
<gidredirect oldgid="uk.org.publicwhip/lords/2022-02-10b.1816.3" newgid="uk.org.publicwhip/lords/2022-02-10c.1816.3" matchtype="perfectmatch"/>
<gidredirect oldgid="uk.org.publicwhip/lords/2022-02-10b.1816.4" newgid="uk.org.publicwhip/lords/2022-02-10c.1816.4" matchtype="perfectmatch"/>
<gidredirect oldgid="uk.org.publicwhip/lords/2022-02-10b.1816.5" newgid="uk.org.publicwhip/lords/2022-02-10c.1816.5" matchtype="perfectmatch"/>
<gidredirect oldgid="uk.org.publicwhip/lords/2022-02-10b.1816.6" newgid="uk.org.publicwhip/lords/2022-02-10c.1816.6" matchtype="perfectmatch"/>
<gidredirect oldgid="uk.org.publicwhip/lords/2022-02-10b.1816.7" newgid="uk.org.publicwhip/lords/2022-02-10c.1816.7" matchtype="perfectmatch"/>
<gidredirect oldgid="uk.org.publicwhip/lords/2022-02-10b.1817.0" newgid="uk.org.publicwhip/lords/2022-02-10c.1817.0" matchtype="perfectmatch"/>
<gidredirect oldgid="uk.org.publicwhip/lords/2022-02-10b.1817.1" newgid="uk.org.publicwhip/lords/2022-02-10c.1817.1" matchtype="perfectmatch"/>
<gidredirect oldgid="uk.org.publicwhip/lords/2022-02-10b.1817.2" newgid="uk.org.publicwhip/lords/2022-02-10c.1817.2" matchtype="perfectmatch"/>
<gidredirect oldgid="uk.org.publicwhip/lords/2022-02-10b.1817.3" newgid="uk.org.publicwhip/lords/2022-02-10c.1817.3" matchtype="perfectmatch"/>
<gidredirect oldgid="uk.org.publicwhip/lords/2022-02-10b.1817.4" newgid="uk.org.publicwhip/lords/2022-02-10c.1817.4" matchtype="perfectmatch"/>
<gidredirect oldgid="uk.org.publicwhip/lords/2022-02-10b.1817.5" newgid="uk.org.publicwhip/lords/2022-02-10c.1817.5" matchtype="perfectmatch"/>
<gidredirect oldgid="uk.org.publicwhip/lords/2022-02-10b.1817.6" newgid="uk.org.publicwhip/lords/2022-02-10c.1817.6" matchtype="perfectmatch"/>
<gidredirect oldgid="uk.org.publicwhip/lords/2022-02-10b.1818.0" newgid="uk.org.publicwhip/lords/2022-02-10c.1818.0" matchtype="perfectmatch"/>
<gidredirect oldgid="uk.org.publicwhip/lords/2022-02-10b.1818.1" newgid="uk.org.publicwhip/lords/2022-02-10c.1818.1" matchtype="perfectmatch"/>
<gidredirect oldgid="uk.org.publicwhip/lords/2022-02-10b.1818.2" newgid="uk.org.publicwhip/lords/2022-02-10c.1818.2" matchtype="perfectmatch"/>
<gidredirect oldgid="uk.org.publicwhip/lords/2022-02-10b.1818.3" newgid="uk.org.publicwhip/lords/2022-02-10c.1818.3" matchtype="perfectmatch"/>
<gidredirect oldgid="uk.org.publicwhip/lords/2022-02-10b.1818.4" newgid="uk.org.publicwhip/lords/2022-02-10c.1818.4" matchtype="perfectmatch"/>
<gidredirect oldgid="uk.org.publicwhip/lords/2022-02-10b.1818.5" newgid="uk.org.publicwhip/lords/2022-02-10c.1818.5" matchtype="perfectmatch"/>
<gidredirect oldgid="uk.org.publicwhip/lords/2022-02-10b.1818.6" newgid="uk.org.publicwhip/lords/2022-02-10c.1818.6" matchtype="perfectmatch"/>
<gidredirect oldgid="uk.org.publicwhip/lords/2022-02-10b.1818.7" newgid="uk.org.publicwhip/lords/2022-02-10c.1818.7" matchtype="perfectmatch"/>
<gidredirect oldgid="uk.org.publicwhip/lords/2022-02-10b.1819.0" newgid="uk.org.publicwhip/lords/2022-02-10c.1819.0" matchtype="perfectmatch"/>
<gidredirect oldgid="uk.org.publicwhip/lords/2022-02-10b.1819.1" newgid="uk.org.publicwhip/lords/2022-02-10c.1819.1" matchtype="perfectmatch"/>
<gidredirect oldgid="uk.org.publicwhip/lords/2022-02-10b.1819.2" newgid="uk.org.publicwhip/lords/2022-02-10c.1819.2" matchtype="perfectmatch"/>
<gidredirect oldgid="uk.org.publicwhip/lords/2022-02-10b.1819.3" newgid="uk.org.publicwhip/lords/2022-02-10c.1819.3" matchtype="perfectmatch"/>
<gidredirect oldgid="uk.org.publicwhip/lords/2022-02-10b.1819.4" newgid="uk.org.publicwhip/lords/2022-02-10c.1819.4" matchtype="perfectmatch"/>
<gidredirect oldgid="uk.org.publicwhip/lords/2022-02-10b.1819.5" newgid="uk.org.publicwhip/lords/2022-02-10c.1819.5" matchtype="perfectmatch"/>
<gidredirect oldgid="uk.org.publicwhip/lords/2022-02-10b.1819.6" newgid="uk.org.publicwhip/lords/2022-02-10c.1819.6" matchtype="perfectmatch"/>
<gidredirect oldgid="uk.org.publicwhip/lords/2022-02-10b.1820.0" newgid="uk.org.publicwhip/lords/2022-02-10c.1820.0" matchtype="perfectmatch"/>
<gidredirect oldgid="uk.org.publicwhip/lords/2022-02-10b.1820.1" newgid="uk.org.publicwhip/lords/2022-02-10c.1820.1" matchtype="perfectmatch"/>
<gidredirect oldgid="uk.org.publicwhip/lords/2022-02-10b.1820.2" newgid="uk.org.publicwhip/lords/2022-02-10c.1820.2" matchtype="perfectmatch"/>
<gidredirect oldgid="uk.org.publicwhip/lords/2022-02-10b.1820.3" newgid="uk.org.publicwhip/lords/2022-02-10c.1820.3" matchtype="perfectmatch"/>
<gidredirect oldgid="uk.org.publicwhip/lords/2022-02-10b.1820.4" newgid="uk.org.publicwhip/lords/2022-02-10c.1820.4" matchtype="perfectmatch"/>
<gidredirect oldgid="uk.org.publicwhip/lords/2022-02-10b.1821.0" newgid="uk.org.publicwhip/lords/2022-02-10c.1821.0" matchtype="perfectmatch"/>
<gidredirect oldgid="uk.org.publicwhip/lords/2022-02-10b.1821.1" newgid="uk.org.publicwhip/lords/2022-02-10c.1821.1" matchtype="perfectmatch"/>
<gidredirect oldgid="uk.org.publicwhip/lords/2022-02-10b.1821.2" newgid="uk.org.publicwhip/lords/2022-02-10c.1821.2" matchtype="perfectmatch"/>
<gidredirect oldgid="uk.org.publicwhip/lords/2022-02-10b.1821.3" newgid="uk.org.publicwhip/lords/2022-02-10c.1821.3" matchtype="perfectmatch"/>
<gidredirect oldgid="uk.org.publicwhip/lords/2022-02-10b.1821.4" newgid="uk.org.publicwhip/lords/2022-02-10c.1821.4" matchtype="perfectmatch"/>
<gidredirect oldgid="uk.org.publicwhip/lords/2022-02-10b.1821.5" newgid="uk.org.publicwhip/lords/2022-02-10c.1821.5" matchtype="perfectmatch"/>
<gidredirect oldgid="uk.org.publicwhip/lords/2022-02-10b.1822.0" newgid="uk.org.publicwhip/lords/2022-02-10c.1822.0" matchtype="perfectmatch"/>
<gidredirect oldgid="uk.org.publicwhip/lords/2022-02-10b.1822.1" newgid="uk.org.publicwhip/lords/2022-02-10c.1822.1" matchtype="perfectmatch"/>
<gidredirect oldgid="uk.org.publicwhip/lords/2022-02-10b.1822.2" newgid="uk.org.publicwhip/lords/2022-02-10c.1822.2" matchtype="perfectmatch"/>
<gidredirect oldgid="uk.org.publicwhip/lords/2022-02-10b.1822.3" newgid="uk.org.publicwhip/lords/2022-02-10c.1822.3" matchtype="perfectmatch"/>
<gidredirect oldgid="uk.org.publicwhip/lords/2022-02-10b.1822.4" newgid="uk.org.publicwhip/lords/2022-02-10c.1822.4" matchtype="perfectmatch"/>
<gidredirect oldgid="uk.org.publicwhip/lords/2022-02-10b.1822.5" newgid="uk.org.publicwhip/lords/2022-02-10c.1822.5" matchtype="perfectmatch"/>
<gidredirect oldgid="uk.org.publicwhip/lords/2022-02-10b.1822.6" newgid="uk.org.publicwhip/lords/2022-02-10c.1822.6" matchtype="perfectmatch"/>
<gidredirect oldgid="uk.org.publicwhip/lords/2022-02-10b.1823.0" newgid="uk.org.publicwhip/lords/2022-02-10c.1823.0" matchtype="perfectmatch"/>
<gidredirect oldgid="uk.org.publicwhip/lords/2022-02-10b.1823.1" newgid="uk.org.publicwhip/lords/2022-02-10c.1823.1" matchtype="perfectmatch"/>
<gidredirect oldgid="uk.org.publicwhip/lords/2022-02-10b.1823.2" newgid="uk.org.publicwhip/lords/2022-02-10c.1823.2" matchtype="perfectmatch"/>
<gidredirect oldgid="uk.org.publicwhip/lords/2022-02-10b.1823.3" newgid="uk.org.publicwhip/lords/2022-02-10c.1823.3" matchtype="perfectmatch"/>
<gidredirect oldgid="uk.org.publicwhip/lords/2022-02-10b.1824.0" newgid="uk.org.publicwhip/lords/2022-02-10c.1824.0" matchtype="perfectmatch"/>
<gidredirect oldgid="uk.org.publicwhip/lords/2022-02-10b.1824.1" newgid="uk.org.publicwhip/lords/2022-02-10c.1824.1" matchtype="perfectmatch"/>
<gidredirect oldgid="uk.org.publicwhip/lords/2022-02-10b.1824.2" newgid="uk.org.publicwhip/lords/2022-02-10c.1824.2" matchtype="perfectmatch"/>
<gidredirect oldgid="uk.org.publicwhip/lords/2022-02-10b.1824.3" newgid="uk.org.publicwhip/lords/2022-02-10c.1824.3" matchtype="perfectmatch"/>
<gidredirect oldgid="uk.org.publicwhip/lords/2022-02-10b.1824.4" newgid="uk.org.publicwhip/lords/2022-02-10c.1824.4" matchtype="perfectmatch"/>
<gidredirect oldgid="uk.org.publicwhip/lords/2022-02-10b.1824.5" newgid="uk.org.publicwhip/lords/2022-02-10c.1824.5" matchtype="perfectmatch"/>
<gidredirect oldgid="uk.org.publicwhip/lords/2022-02-10b.1824.6" newgid="uk.org.publicwhip/lords/2022-02-10c.1824.6" matchtype="perfectmatch"/>
<gidredirect oldgid="uk.org.publicwhip/lords/2022-02-10b.1825.0" newgid="uk.org.publicwhip/lords/2022-02-10c.1825.0" matchtype="perfectmatch"/>
<gidredirect oldgid="uk.org.publicwhip/lords/2022-02-10b.1825.1" newgid="uk.org.publicwhip/lords/2022-02-10c.1825.1" matchtype="perfectmatch"/>
<gidredirect oldgid="uk.org.publicwhip/lords/2022-02-10b.1825.2" newgid="uk.org.publicwhip/lords/2022-02-10c.1825.2" matchtype="perfectmatch"/>
<gidredirect oldgid="uk.org.publicwhip/lords/2022-02-10b.1825.3" newgid="uk.org.publicwhip/lords/2022-02-10c.1825.3" matchtype="perfectmatch"/>
<gidredirect oldgid="uk.org.publicwhip/lords/2022-02-10b.1825.4" newgid="uk.org.publicwhip/lords/2022-02-10c.1825.4" matchtype="perfectmatch"/>
<gidredirect oldgid="uk.org.publicwhip/lords/2022-02-10b.1825.5" newgid="uk.org.publicwhip/lords/2022-02-10c.1825.5" matchtype="perfectmatch"/>
<gidredirect oldgid="uk.org.publicwhip/lords/2022-02-10b.1825.6" newgid="uk.org.publicwhip/lords/2022-02-10c.1825.6" matchtype="perfectmatch"/>
<gidredirect oldgid="uk.org.publicwhip/lords/2022-02-10b.1826.0" newgid="uk.org.publicwhip/lords/2022-02-10c.1826.0" matchtype="perfectmatch"/>
<gidredirect oldgid="uk.org.publicwhip/lords/2022-02-10b.1826.1" newgid="uk.org.publicwhip/lords/2022-02-10c.1826.1" matchtype="perfectmatch"/>
<gidredirect oldgid="uk.org.publicwhip/lords/2022-02-10b.1826.2" newgid="uk.org.publicwhip/lords/2022-02-10c.1826.2" matchtype="perfectmatch"/>
<gidredirect oldgid="uk.org.publicwhip/lords/2022-02-10b.1826.3" newgid="uk.org.publicwhip/lords/2022-02-10c.1826.3" matchtype="perfectmatch"/>
<gidredirect oldgid="uk.org.publicwhip/lords/2022-02-10b.1826.4" newgid="uk.org.publicwhip/lords/2022-02-10c.1826.4" matchtype="perfectmatch"/>
<gidredirect oldgid="uk.org.publicwhip/lords/2022-02-10b.1827.0" newgid="uk.org.publicwhip/lords/2022-02-10c.1827.0" matchtype="perfectmatch"/>
<gidredirect oldgid="uk.org.publicwhip/lords/2022-02-10b.1827.1" newgid="uk.org.publicwhip/lords/2022-02-10c.1827.1" matchtype="perfectmatch"/>
<gidredirect oldgid="uk.org.publicwhip/lords/2022-02-10b.1827.2" newgid="uk.org.publicwhip/lords/2022-02-10c.1827.2" matchtype="perfectmatch"/>
<gidredirect oldgid="uk.org.publicwhip/lords/2022-02-10b.1827.3" newgid="uk.org.publicwhip/lords/2022-02-10c.1827.3" matchtype="perfectmatch"/>
<gidredirect oldgid="uk.org.publicwhip/lords/2022-02-10b.1827.4" newgid="uk.org.publicwhip/lords/2022-02-10c.1827.4" matchtype="perfectmatch"/>
<gidredirect oldgid="uk.org.publicwhip/lords/2022-02-10b.1827.5" newgid="uk.org.publicwhip/lords/2022-02-10c.1827.5" matchtype="perfectmatch"/>
<gidredirect oldgid="uk.org.publicwhip/lords/2022-02-10b.1827.6" newgid="uk.org.publicwhip/lords/2022-02-10c.1827.6" matchtype="perfectmatch"/>
<gidredirect oldgid="uk.org.publicwhip/lords/2022-02-10b.1827.7" newgid="uk.org.publicwhip/lords/2022-02-10c.1827.7" matchtype="perfectmatch"/>
<gidredirect oldgid="uk.org.publicwhip/lords/2022-02-10b.1828.0" newgid="uk.org.publicwhip/lords/2022-02-10c.1828.0" matchtype="perfectmatch"/>
<gidredirect oldgid="uk.org.publicwhip/lords/2022-02-10b.1828.1" newgid="uk.org.publicwhip/lords/2022-02-10c.1828.1" matchtype="perfectmatch"/>
<gidredirect oldgid="uk.org.publicwhip/lords/2022-02-10b.1828.2" newgid="uk.org.publicwhip/lords/2022-02-10c.1828.2" matchtype="perfectmatch"/>
<gidredirect oldgid="uk.org.publicwhip/lords/2022-02-10b.1828.3" newgid="uk.org.publicwhip/lords/2022-02-10c.1828.3" matchtype="perfectmatch"/>
<gidredirect oldgid="uk.org.publicwhip/lords/2022-02-10b.1828.4" newgid="uk.org.publicwhip/lords/2022-02-10c.1828.4" matchtype="perfectmatch"/>
<gidredirect oldgid="uk.org.publicwhip/lords/2022-02-10b.1828.5" newgid="uk.org.publicwhip/lords/2022-02-10c.1828.5" matchtype="perfectmatch"/>
<gidredirect oldgid="uk.org.publicwhip/lords/2022-02-10b.1828.6" newgid="uk.org.publicwhip/lords/2022-02-10c.1828.6" matchtype="perfectmatch"/>
<gidredirect oldgid="uk.org.publicwhip/lords/2022-02-10b.1828.7" newgid="uk.org.publicwhip/lords/2022-02-10c.1828.7" matchtype="perfectmatch"/>
<gidredirect oldgid="uk.org.publicwhip/lords/2022-02-10b.1828.8" newgid="uk.org.publicwhip/lords/2022-02-10c.1828.8" matchtype="perfectmatch"/>
<gidredirect oldgid="uk.org.publicwhip/lords/2022-02-10b.1828.9" newgid="uk.org.publicwhip/lords/2022-02-10c.1828.9" matchtype="perfectmatch"/>
<gidredirect oldgid="uk.org.publicwhip/lords/2022-02-10b.1828.10" newgid="uk.org.publicwhip/lords/2022-02-10c.1828.10" matchtype="perfectmatch"/>
<gidredirect oldgid="uk.org.publicwhip/lords/2022-02-10b.1829.0" newgid="uk.org.publicwhip/lords/2022-02-10c.1829.0" matchtype="perfectmatch"/>
<gidredirect oldgid="uk.org.publicwhip/lords/2022-02-10b.1832.0" newgid="uk.org.publicwhip/lords/2022-02-10c.1832.0" matchtype="perfectmatch"/>
<gidredirect oldgid="uk.org.publicwhip/lords/2022-02-10b.1833.0" newgid="uk.org.publicwhip/lords/2022-02-10c.1833.0" matchtype="perfectmatch"/>
<gidredirect oldgid="uk.org.publicwhip/lords/2022-02-10b.1834.0" newgid="uk.org.publicwhip/lords/2022-02-10c.1834.0" matchtype="perfectmatch"/>
<gidredirect oldgid="uk.org.publicwhip/lords/2022-02-10b.1835.0" newgid="uk.org.publicwhip/lords/2022-02-10c.1835.0" matchtype="perfectmatch"/>
<gidredirect oldgid="uk.org.publicwhip/lords/2022-02-10b.1836.0" newgid="uk.org.publicwhip/lords/2022-02-10c.1836.0" matchtype="perfectmatch"/>
<gidredirect oldgid="uk.org.publicwhip/lords/2022-02-10b.1837.0" newgid="uk.org.publicwhip/lords/2022-02-10c.1837.0" matchtype="perfectmatch"/>
<gidredirect oldgid="uk.org.publicwhip/lords/2022-02-10b.1838.0" newgid="uk.org.publicwhip/lords/2022-02-10c.1838.0" matchtype="perfectmatch"/>
<gidredirect oldgid="uk.org.publicwhip/lords/2022-02-10b.1839.0" newgid="uk.org.publicwhip/lords/2022-02-10c.1839.0" matchtype="perfectmatch"/>
<gidredirect oldgid="uk.org.publicwhip/lords/2022-02-10b.1840.0" newgid="uk.org.publicwhip/lords/2022-02-10c.1840.0" matchtype="perfectmatch"/>
<gidredirect oldgid="uk.org.publicwhip/lords/2022-02-10b.1841.0" newgid="uk.org.publicwhip/lords/2022-02-10c.1841.0" matchtype="perfectmatch"/>
<gidredirect oldgid="uk.org.publicwhip/lords/2022-02-10b.1841.1" newgid="uk.org.publicwhip/lords/2022-02-10c.1841.1" matchtype="perfectmatch"/>
<gidredirect oldgid="uk.org.publicwhip/lords/2022-02-10b.1841.2" newgid="uk.org.publicwhip/lords/2022-02-10c.1841.2" matchtype="perfectmatch"/>
<gidredirect oldgid="uk.org.publicwhip/lords/2022-02-10b.1841.3" newgid="uk.org.publicwhip/lords/2022-02-10c.1841.3" matchtype="perfectmatch"/>
<gidredirect oldgid="uk.org.publicwhip/lords/2022-02-10b.1842.0" newgid="uk.org.publicwhip/lords/2022-02-10c.1842.0" matchtype="perfectmatch"/>
<gidredirect oldgid="uk.org.publicwhip/lords/2022-02-10b.1842.1" newgid="uk.org.publicwhip/lords/2022-02-10c.1842.1" matchtype="perfectmatch"/>
<gidredirect oldgid="uk.org.publicwhip/lords/2022-02-10b.1843.0" newgid="uk.org.publicwhip/lords/2022-02-10c.1843.0" matchtype="perfectmatch"/>
<gidredirect oldgid="uk.org.publicwhip/lords/2022-02-10b.1843.1" newgid="uk.org.publicwhip/lords/2022-02-10c.1843.1" matchtype="perfectmatch"/>
<gidredirect oldgid="uk.org.publicwhip/lords/2022-02-10b.1843.2" newgid="uk.org.publicwhip/lords/2022-02-10c.1843.2" matchtype="perfectmatch"/>
<gidredirect oldgid="uk.org.publicwhip/lords/2022-02-10b.1843.3" newgid="uk.org.publicwhip/lords/2022-02-10c.1843.3" matchtype="perfectmatch"/>
<gidredirect oldgid="uk.org.publicwhip/lords/2022-02-10b.1844.0" newgid="uk.org.publicwhip/lords/2022-02-10c.1844.0" matchtype="perfectmatch"/>
<gidredirect oldgid="uk.org.publicwhip/lords/2022-02-10b.1845.0" newgid="uk.org.publicwhip/lords/2022-02-10c.1845.0" matchtype="perfectmatch"/>
<gidredirect oldgid="uk.org.publicwhip/lords/2022-02-10b.1845.1" newgid="uk.org.publicwhip/lords/2022-02-10c.1845.1" matchtype="perfectmatch"/>
<gidredirect oldgid="uk.org.publicwhip/lords/2022-02-10b.1845.2" newgid="uk.org.publicwhip/lords/2022-02-10c.1845.2" matchtype="perfectmatch"/>
<gidredirect oldgid="uk.org.publicwhip/lords/2022-02-10b.1846.0" newgid="uk.org.publicwhip/lords/2022-02-10c.1846.0" matchtype="perfectmatch"/>
<gidredirect oldgid="uk.org.publicwhip/lords/2022-02-10b.1846.1" newgid="uk.org.publicwhip/lords/2022-02-10c.1846.1" matchtype="perfectmatch"/>
<gidredirect oldgid="uk.org.publicwhip/lords/2022-02-10b.1846.2" newgid="uk.org.publicwhip/lords/2022-02-10c.1846.2" matchtype="perfectmatch"/>
<gidredirect oldgid="uk.org.publicwhip/lords/2022-02-10b.1847.0" newgid="uk.org.publicwhip/lords/2022-02-10c.1847.0" matchtype="perfectmatch"/>
<gidredirect oldgid="uk.org.publicwhip/lords/2022-02-10b.1847.1" newgid="uk.org.publicwhip/lords/2022-02-10c.1847.1" matchtype="perfectmatch"/>
<gidredirect oldgid="uk.org.publicwhip/lords/2022-02-10b.1848.0" newgid="uk.org.publicwhip/lords/2022-02-10c.1848.0" matchtype="perfectmatch"/>
<gidredirect oldgid="uk.org.publicwhip/lords/2022-02-10b.1848.1" newgid="uk.org.publicwhip/lords/2022-02-10c.1848.1" matchtype="perfectmatch"/>
<gidredirect oldgid="uk.org.publicwhip/lords/2022-02-10b.1848.2" newgid="uk.org.publicwhip/lords/2022-02-10c.1848.2" matchtype="perfectmatch"/>
<gidredirect oldgid="uk.org.publicwhip/lords/2022-02-10b.1848.3" newgid="uk.org.publicwhip/lords/2022-02-10c.1848.3" matchtype="perfectmatch"/>
<gidredirect oldgid="uk.org.publicwhip/lords/2022-02-10b.1848.4" newgid="uk.org.publicwhip/lords/2022-02-10c.1848.4" matchtype="perfectmatch"/>
<gidredirect oldgid="uk.org.publicwhip/lords/2022-02-10b.1849.0" newgid="uk.org.publicwhip/lords/2022-02-10c.1849.0" matchtype="perfectmatch"/>
<gidredirect oldgid="uk.org.publicwhip/lords/2022-02-10b.1849.1" newgid="uk.org.publicwhip/lords/2022-02-10c.1849.1" matchtype="perfectmatch"/>
<gidredirect oldgid="uk.org.publicwhip/lords/2022-02-10b.1849.2" newgid="uk.org.publicwhip/lords/2022-02-10c.1849.2" matchtype="perfectmatch"/>
<gidredirect oldgid="uk.org.publicwhip/lords/2022-02-10b.1850.0" newgid="uk.org.publicwhip/lords/2022-02-10c.1850.0" matchtype="perfectmatch"/>
<gidredirect oldgid="uk.org.publicwhip/lords/2022-02-10b.1850.1" newgid="uk.org.publicwhip/lords/2022-02-10c.1850.1" matchtype="perfectmatch"/>
<gidredirect oldgid="uk.org.publicwhip/lords/2022-02-10b.1853.0" newgid="uk.org.publicwhip/lords/2022-02-10c.1853.0" matchtype="perfectmatch"/>
<gidredirect oldgid="uk.org.publicwhip/lords/2022-02-10b.1855.0" newgid="uk.org.publicwhip/lords/2022-02-10c.1855.0" matchtype="perfectmatch"/>
<gidredirect oldgid="uk.org.publicwhip/lords/2022-02-10b.1855.1" newgid="uk.org.publicwhip/lords/2022-02-10c.1855.1" matchtype="perfectmatch"/>
<gidredirect oldgid="uk.org.publicwhip/lords/2022-02-10b.1856.0" newgid="uk.org.publicwhip/lords/2022-02-10c.1856.0" matchtype="perfectmatch"/>
<gidredirect oldgid="uk.org.publicwhip/lords/2022-02-10b.1856.1" newgid="uk.org.publicwhip/lords/2022-02-10c.1856.1" matchtype="perfectmatch"/>
<gidredirect oldgid="uk.org.publicwhip/lords/2022-02-10b.1857.0" newgid="uk.org.publicwhip/lords/2022-02-10c.1857.0" matchtype="perfectmatch"/>
<gidredirect oldgid="uk.org.publicwhip/lords/2022-02-10b.1857.1" newgid="uk.org.publicwhip/lords/2022-02-10c.1857.1" matchtype="perfectmatch"/>
<gidredirect oldgid="uk.org.publicwhip/lords/2022-02-10b.1857.2" newgid="uk.org.publicwhip/lords/2022-02-10c.1857.2" matchtype="perfectmatch"/>
<gidredirect oldgid="uk.org.publicwhip/lords/2022-02-10b.1857.3" newgid="uk.org.publicwhip/lords/2022-02-10c.1857.3" matchtype="perfectmatch"/>
<gidredirect oldgid="uk.org.publicwhip/lords/2022-02-10b.1857.4" newgid="uk.org.publicwhip/lords/2022-02-10c.1857.4" matchtype="perfectmatch"/>
<gidredirect oldgid="uk.org.publicwhip/lords/2022-02-10b.1858.0" newgid="uk.org.publicwhip/lords/2022-02-10c.1858.0" matchtype="perfectmatch"/>
<gidredirect oldgid="uk.org.publicwhip/lords/2022-02-10b.1860.0" newgid="uk.org.publicwhip/lords/2022-02-10c.1860.0" matchtype="perfectmatch"/>
<gidredirect oldgid="uk.org.publicwhip/lords/2022-02-10b.1860.1" newgid="uk.org.publicwhip/lords/2022-02-10c.1860.1" matchtype="perfectmatch"/>
<gidredirect oldgid="uk.org.publicwhip/lords/2022-02-10b.1861.0" newgid="uk.org.publicwhip/lords/2022-02-10c.1861.0" matchtype="perfectmatch"/>
<gidredirect oldgid="uk.org.publicwhip/lords/2022-02-10b.1861.1" newgid="uk.org.publicwhip/lords/2022-02-10c.1861.1" matchtype="perfectmatch"/>
<gidredirect oldgid="uk.org.publicwhip/lords/2022-02-10b.1862.0" newgid="uk.org.publicwhip/lords/2022-02-10c.1862.0" matchtype="perfectmatch"/>
<gidredirect oldgid="uk.org.publicwhip/lords/2022-02-10b.1862.1" newgid="uk.org.publicwhip/lords/2022-02-10c.1862.1" matchtype="perfectmatch"/>
<gidredirect oldgid="uk.org.publicwhip/lords/2022-02-10b.1862.2" newgid="uk.org.publicwhip/lords/2022-02-10c.1862.2" matchtype="perfectmatch"/>
<gidredirect oldgid="uk.org.publicwhip/lords/2022-02-10b.1862.3" newgid="uk.org.publicwhip/lords/2022-02-10c.1862.3" matchtype="perfectmatch"/>
<gidredirect oldgid="uk.org.publicwhip/lords/2022-02-10b.1862.4" newgid="uk.org.publicwhip/lords/2022-02-10c.1862.4" matchtype="perfectmatch"/>
<gidredirect oldgid="uk.org.publicwhip/lords/2022-02-10b.1863.0" newgid="uk.org.publicwhip/lords/2022-02-10c.1863.0" matchtype="perfectmatch"/>
<gidredirect oldgid="uk.org.publicwhip/lords/2022-02-10b.1863.1" newgid="uk.org.publicwhip/lords/2022-02-10c.1863.1" matchtype="perfectmatch"/>
<gidredirect oldgid="uk.org.publicwhip/lords/2022-02-10b.1863.2" newgid="uk.org.publicwhip/lords/2022-02-10c.1863.2" matchtype="perfectmatch"/>
<gidredirect oldgid="uk.org.publicwhip/lords/2022-02-10b.1863.3" newgid="uk.org.publicwhip/lords/2022-02-10c.1863.3" matchtype="perfectmatch"/>
<gidredirect oldgid="uk.org.publicwhip/lords/2022-02-10b.1863.4" newgid="uk.org.publicwhip/lords/2022-02-10c.1863.4" matchtype="perfectmatch"/>
<gidredirect oldgid="uk.org.publicwhip/lords/2022-02-10b.1863.5" newgid="uk.org.publicwhip/lords/2022-02-10c.1863.5" matchtype="perfectmatch"/>
<gidredirect oldgid="uk.org.publicwhip/lords/2022-02-10b.1864.0" newgid="uk.org.publicwhip/lords/2022-02-10c.1864.0" matchtype="perfectmatch"/>
<gidredirect oldgid="uk.org.publicwhip/lords/2022-02-10b.1864.1" newgid="uk.org.publicwhip/lords/2022-02-10c.1864.1" matchtype="perfectmatch"/>
<gidredirect oldgid="uk.org.publicwhip/lords/2022-02-10b.1864.2" newgid="uk.org.publicwhip/lords/2022-02-10c.1864.2" matchtype="perfectmatch"/>
<gidredirect oldgid="uk.org.publicwhip/lords/2022-02-10b.1864.3" newgid="uk.org.publicwhip/lords/2022-02-10c.1864.3" matchtype="perfectmatch"/>
<gidredirect oldgid="uk.org.publicwhip/lords/2022-02-10b.1864.4" newgid="uk.org.publicwhip/lords/2022-02-10c.1864.4" matchtype="perfectmatch"/>
<gidredirect oldgid="uk.org.publicwhip/lords/2022-02-10b.1865.0" newgid="uk.org.publicwhip/lords/2022-02-10c.1865.0" matchtype="perfectmatch"/>
<gidredirect oldgid="uk.org.publicwhip/lords/2022-02-10b.1865.1" newgid="uk.org.publicwhip/lords/2022-02-10c.1865.1" matchtype="perfectmatch"/>
<gidredirect oldgid="uk.org.publicwhip/lords/2022-02-10b.1865.2" newgid="uk.org.publicwhip/lords/2022-02-10c.1865.2" matchtype="perfectmatch"/>
<gidredirect oldgid="uk.org.publicwhip/lords/2022-02-10b.1865.3" newgid="uk.org.publicwhip/lords/2022-02-10c.1865.3" matchtype="perfectmatch"/>
<gidredirect oldgid="uk.org.publicwhip/lords/2022-02-10b.1865.4" newgid="uk.org.publicwhip/lords/2022-02-10c.1865.4" matchtype="perfectmatch"/>
<gidredirect oldgid="uk.org.publicwhip/lords/2022-02-10b.1866.0" newgid="uk.org.publicwhip/lords/2022-02-10c.1866.0" matchtype="perfectmatch"/>
<gidredirect oldgid="uk.org.publicwhip/lords/2022-02-10b.1866.1" newgid="uk.org.publicwhip/lords/2022-02-10c.1866.1" matchtype="perfectmatch"/>
<gidredirect oldgid="uk.org.publicwhip/lords/2022-02-10b.1866.2" newgid="uk.org.publicwhip/lords/2022-02-10c.1866.2" matchtype="perfectmatch"/>
<gidredirect oldgid="uk.org.publicwhip/lords/2022-02-10b.1868.0" newgid="uk.org.publicwhip/lords/2022-02-10c.1868.0" matchtype="perfectmatch"/>
<gidredirect oldgid="uk.org.publicwhip/lords/2022-02-10b.1869.0" newgid="uk.org.publicwhip/lords/2022-02-10c.1869.0" matchtype="perfectmatch"/>
<gidredirect oldgid="uk.org.publicwhip/lords/2022-02-10b.1870.0" newgid="uk.org.publicwhip/lords/2022-02-10c.1870.0" matchtype="perfectmatch"/>
<gidredirect oldgid="uk.org.publicwhip/lords/2022-02-10b.1871.0" newgid="uk.org.publicwhip/lords/2022-02-10c.1871.0" matchtype="perfectmatch"/>
<gidredirect oldgid="uk.org.publicwhip/lords/2022-02-10b.1872.0" newgid="uk.org.publicwhip/lords/2022-02-10c.1872.0" matchtype="perfectmatch"/>
<gidredirect oldgid="uk.org.publicwhip/lords/2022-02-10b.1872.1" newgid="uk.org.publicwhip/lords/2022-02-10c.1872.1" matchtype="perfectmatch"/>
<gidredirect oldgid="uk.org.publicwhip/lords/2022-02-10b.1873.0" newgid="uk.org.publicwhip/lords/2022-02-10c.1873.0" matchtype="perfectmatch"/>
<gidredirect oldgid="uk.org.publicwhip/lords/2022-02-10b.1874.0" newgid="uk.org.publicwhip/lords/2022-02-10c.1874.0" matchtype="perfectmatch"/>
<gidredirect oldgid="uk.org.publicwhip/lords/2022-02-10b.1875.0" newgid="uk.org.publicwhip/lords/2022-02-10c.1875.0" matchtype="perfectmatch"/>
<gidredirect oldgid="uk.org.publicwhip/lords/2022-02-10b.1875.1" newgid="uk.org.publicwhip/lords/2022-02-10c.1875.1" matchtype="perfectmatch"/>
<gidredirect oldgid="uk.org.publicwhip/lords/2022-02-10b.1875.2" newgid="uk.org.publicwhip/lords/2022-02-10c.1875.2" matchtype="perfectmatch"/>
<gidredirect oldgid="uk.org.publicwhip/lords/2022-02-10b.1875.3" newgid="uk.org.publicwhip/lords/2022-02-10c.1875.3" matchtype="perfectmatch"/>
<gidredirect oldgid="uk.org.publicwhip/lords/2022-02-10b.1876.0" newgid="uk.org.publicwhip/lords/2022-02-10c.1876.0" matchtype="perfectmatch"/>
<gidredirect oldgid="uk.org.publicwhip/lords/2022-02-10b.1876.1" newgid="uk.org.publicwhip/lords/2022-02-10c.1876.1" matchtype="perfectmatch"/>
<gidredirect oldgid="uk.org.publicwhip/lords/2022-02-10b.1878.0" newgid="uk.org.publicwhip/lords/2022-02-10c.1878.0" matchtype="perfectmatch"/>
<gidredirect oldgid="uk.org.publicwhip/lords/2022-02-10b.1878.1" newgid="uk.org.publicwhip/lords/2022-02-10c.1878.1" matchtype="perfectmatch"/>
<gidredirect oldgid="uk.org.publicwhip/lords/2022-02-10b.1879.0" newgid="uk.org.publicwhip/lords/2022-02-10c.1879.0" matchtype="perfectmatch"/>
<gidredirect oldgid="uk.org.publicwhip/lords/2022-02-10b.1880.0" newgid="uk.org.publicwhip/lords/2022-02-10c.1880.0" matchtype="perfectmatch"/>
<gidredirect oldgid="uk.org.publicwhip/lords/2022-02-10b.1880.1" newgid="uk.org.publicwhip/lords/2022-02-10c.1880.1" matchtype="perfectmatch"/>
<gidredirect oldgid="uk.org.publicwhip/lords/2022-02-10b.1880.2" newgid="uk.org.publicwhip/lords/2022-02-10c.1880.2" matchtype="perfectmatch"/>
<gidredirect oldgid="uk.org.publicwhip/lords/2022-02-10b.1883.0" newgid="uk.org.publicwhip/lords/2022-02-10c.1883.0" matchtype="perfectmatch"/>
<gidredirect oldgid="uk.org.publicwhip/lords/2022-02-10b.1885.0" newgid="uk.org.publicwhip/lords/2022-02-10c.1885.0" matchtype="perfectmatch"/>
<gidredirect oldgid="uk.org.publicwhip/lords/2022-02-10b.1887.0" newgid="uk.org.publicwhip/lords/2022-02-10c.1887.0" matchtype="perfectmatch"/>
<gidredirect oldgid="uk.org.publicwhip/lords/2022-02-10b.1888.0" newgid="uk.org.publicwhip/lords/2022-02-10c.1888.0" matchtype="perfectmatch"/>
<gidredirect oldgid="uk.org.publicwhip/lords/2022-02-10b.1888.1" newgid="uk.org.publicwhip/lords/2022-02-10c.1888.1" matchtype="perfectmatch"/>
<gidredirect oldgid="uk.org.publicwhip/lords/2022-02-10b.1889.0" newgid="uk.org.publicwhip/lords/2022-02-10c.1889.0" matchtype="perfectmatch"/>
<gidredirect oldgid="uk.org.publicwhip/lords/2022-02-10b.1891.0" newgid="uk.org.publicwhip/lords/2022-02-10c.1891.0" matchtype="perfectmatch"/>
<gidredirect oldgid="uk.org.publicwhip/lords/2022-02-10b.1892.0" newgid="uk.org.publicwhip/lords/2022-02-10c.1892.0" matchtype="perfectmatch"/>
<gidredirect oldgid="uk.org.publicwhip/lords/2022-02-10b.1892.1" newgid="uk.org.publicwhip/lords/2022-02-10c.1892.1" matchtype="perfectmatch"/>
<gidredirect oldgid="uk.org.publicwhip/lords/2022-02-10b.1894.0" newgid="uk.org.publicwhip/lords/2022-02-10c.1894.0" matchtype="perfectmatch"/>
<gidredirect oldgid="uk.org.publicwhip/lords/2022-02-10b.1896.0" newgid="uk.org.publicwhip/lords/2022-02-10c.1896.0" matchtype="perfectmatch"/>
<gidredirect oldgid="uk.org.publicwhip/lords/2022-02-10b.1896.1" newgid="uk.org.publicwhip/lords/2022-02-10c.1896.1" matchtype="perfectmatch"/>
<gidredirect oldgid="uk.org.publicwhip/lords/2022-02-10b.1898.0" newgid="uk.org.publicwhip/lords/2022-02-10c.1898.0" matchtype="perfectmatch"/>
<gidredirect oldgid="uk.org.publicwhip/lords/2022-02-10b.1900.0" newgid="uk.org.publicwhip/lords/2022-02-10c.1900.0" matchtype="perfectmatch"/>
<gidredirect oldgid="uk.org.publicwhip/lords/2022-02-10b.1901.0" newgid="uk.org.publicwhip/lords/2022-02-10c.1901.0" matchtype="perfectmatch"/>
<gidredirect oldgid="uk.org.publicwhip/lords/2022-02-10b.1901.1" newgid="uk.org.publicwhip/lords/2022-02-10c.1901.1" matchtype="perfectmatch"/>
<gidredirect oldgid="uk.org.publicwhip/lords/2022-02-10b.1902.0" newgid="uk.org.publicwhip/lords/2022-02-10c.1902.0" matchtype="perfectmatch"/>
<gidredirect oldgid="uk.org.publicwhip/lords/2022-02-10b.1902.1" newgid="uk.org.publicwhip/lords/2022-02-10c.1902.1" matchtype="perfectmatch"/>
<gidredirect oldgid="uk.org.publicwhip/lords/2022-02-10b.1902.2" newgid="uk.org.publicwhip/lords/2022-02-10c.1902.2" matchtype="perfectmatch"/>
<gidredirect oldgid="uk.org.publicwhip/lords/2022-02-10b.1902.3" newgid="uk.org.publicwhip/lords/2022-02-10c.1902.3" matchtype="perfectmatch"/>
<gidredirect oldgid="uk.org.publicwhip/lords/2022-02-10b.1902.4" newgid="uk.org.publicwhip/lords/2022-02-10c.1902.4" matchtype="perfectmatch"/>
<gidredirect oldgid="uk.org.publicwhip/lords/2022-02-10b.1903.0" newgid="uk.org.publicwhip/lords/2022-02-10c.1903.0" matchtype="perfectmatch"/>
<gidredirect oldgid="uk.org.publicwhip/lords/2022-02-10b.1903.1" newgid="uk.org.publicwhip/lords/2022-02-10c.1903.1" matchtype="perfectmatch"/>
<gidredirect oldgid="uk.org.publicwhip/lords/2022-02-10b.1903.2" newgid="uk.org.publicwhip/lords/2022-02-10c.1903.2" matchtype="perfectmatch"/>
<gidredirect oldgid="uk.org.publicwhip/lords/2022-02-10b.1903.3" newgid="uk.org.publicwhip/lords/2022-02-10c.1903.3" matchtype="perfectmatch"/>
<gidredirect oldgid="uk.org.publicwhip/lords/2022-02-10b.1904.0" newgid="uk.org.publicwhip/lords/2022-02-10c.1904.0" matchtype="perfectmatch"/>
<gidredirect oldgid="uk.org.publicwhip/lords/2022-02-10b.1904.1" newgid="uk.org.publicwhip/lords/2022-02-10c.1904.1" matchtype="perfectmatch"/>
<gidredirect oldgid="uk.org.publicwhip/lords/2022-02-10b.1904.2" newgid="uk.org.publicwhip/lords/2022-02-10c.1904.2" matchtype="perfectmatch"/>
<gidredirect oldgid="uk.org.publicwhip/lords/2022-02-10b.1904.3" newgid="uk.org.publicwhip/lords/2022-02-10c.1904.3" matchtype="perfectmatch"/>
<gidredirect oldgid="uk.org.publicwhip/lords/2022-02-10b.1904.4" newgid="uk.org.publicwhip/lords/2022-02-10c.1904.4" matchtype="perfectmatch"/>
<gidredirect oldgid="uk.org.publicwhip/lords/2022-02-10b.1904.5" newgid="uk.org.publicwhip/lords/2022-02-10c.1904.5" matchtype="perfectmatch"/>
<gidredirect oldgid="uk.org.publicwhip/lords/2022-02-10b.1904.6" newgid="uk.org.publicwhip/lords/2022-02-10c.1904.6" matchtype="perfectmatch"/>
<gidredirect oldgid="uk.org.publicwhip/lords/2022-02-10b.1904.7" newgid="uk.org.publicwhip/lords/2022-02-10c.1904.7" matchtype="perfectmatch"/>
<gidredirect oldgid="uk.org.publicwhip/lords/2022-02-10b.1905.0" newgid="uk.org.publicwhip/lords/2022-02-10c.1905.0" matchtype="perfectmatch"/>
<gidredirect oldgid="uk.org.publicwhip/lords/2022-02-10b.1906.0" newgid="uk.org.publicwhip/lords/2022-02-10c.1906.0" matchtype="perfectmatch"/>
<gidredirect oldgid="uk.org.publicwhip/lords/2022-02-10b.1907.0" newgid="uk.org.publicwhip/lords/2022-02-10c.1907.0" matchtype="perfectmatch"/>
<gidredirect oldgid="uk.org.publicwhip/lords/2022-02-10b.1908.0" newgid="uk.org.publicwhip/lords/2022-02-10c.1908.0" matchtype="perfectmatch"/>
<gidredirect oldgid="uk.org.publicwhip/lords/2022-02-10b.1908.1" newgid="uk.org.publicwhip/lords/2022-02-10c.1908.1" matchtype="perfectmatch"/>
<gidredirect oldgid="uk.org.publicwhip/lords/2022-02-10b.1909.0" newgid="uk.org.publicwhip/lords/2022-02-10c.1909.0" matchtype="perfectmatch"/>
<gidredirect oldgid="uk.org.publicwhip/lords/2022-02-10b.1910.0" newgid="uk.org.publicwhip/lords/2022-02-10c.1910.0" matchtype="perfectmatch"/>
<gidredirect oldgid="uk.org.publicwhip/lords/2022-02-10b.1910.1" newgid="uk.org.publicwhip/lords/2022-02-10c.1910.1" matchtype="perfectmatch"/>
<gidredirect oldgid="uk.org.publicwhip/lords/2022-02-10b.1910.2" newgid="uk.org.publicwhip/lords/2022-02-10c.1910.2" matchtype="perfectmatch"/>
<gidredirect oldgid="uk.org.publicwhip/lords/2022-02-10b.1912.0" newgid="uk.org.publicwhip/lords/2022-02-10c.1912.0" matchtype="perfectmatch"/>
<gidredirect oldgid="uk.org.publicwhip/lords/2022-02-10b.1913.0" newgid="uk.org.publicwhip/lords/2022-02-10c.1913.0" matchtype="perfectmatch"/>
<gidredirect oldgid="uk.org.publicwhip/lords/2022-02-10b.1915.0" newgid="uk.org.publicwhip/lords/2022-02-10c.1915.0" matchtype="perfectmatch"/>
<gidredirect oldgid="uk.org.publicwhip/lords/2022-02-10b.1917.0" newgid="uk.org.publicwhip/lords/2022-02-10c.1917.0" matchtype="perfectmatch"/>
<gidredirect oldgid="uk.org.publicwhip/lords/2022-02-10b.1917.1" newgid="uk.org.publicwhip/lords/2022-02-10c.1917.1" matchtype="perfectmatch"/>
<gidredirect oldgid="uk.org.publicwhip/lords/2022-02-10b.1918.0" newgid="uk.org.publicwhip/lords/2022-02-10c.1918.0" matchtype="perfectmatch"/>
<gidredirect oldgid="uk.org.publicwhip/lords/2022-02-10b.1919.0" newgid="uk.org.publicwhip/lords/2022-02-10c.1919.0" matchtype="perfectmatch"/>
<gidredirect oldgid="uk.org.publicwhip/lords/2022-02-10b.1919.1" newgid="uk.org.publicwhip/lords/2022-02-10c.1919.1" matchtype="perfectmatch"/>
<gidredirect oldgid="uk.org.publicwhip/lords/2022-02-10b.1920.0" newgid="uk.org.publicwhip/lords/2022-02-10c.1920.0" matchtype="perfectmatch"/>
<gidredirect oldgid="uk.org.publicwhip/lords/2022-02-10b.1922.0" newgid="uk.org.publicwhip/lords/2022-02-10c.1922.0" matchtype="perfectmatch"/>
<gidredirect oldgid="uk.org.publicwhip/lords/2022-02-10b.1922.1" newgid="uk.org.publicwhip/lords/2022-02-10c.1922.1" matchtype="perfectmatch"/>
<gidredirect oldgid="uk.org.publicwhip/lords/2022-02-10b.1922.2" newgid="uk.org.publicwhip/lords/2022-02-10c.1922.2" matchtype="perfectmatch"/>
<gidredirect oldgid="uk.org.publicwhip/lords/2022-02-10b.1922.3" newgid="uk.org.publicwhip/lords/2022-02-10c.1922.3" matchtype="perfectmatch"/>
<gidredirect oldgid="uk.org.publicwhip/lords/2022-02-10b.1923.0" newgid="uk.org.publicwhip/lords/2022-02-10c.1923.0" matchtype="perfectmatch"/>
<gidredirect oldgid="uk.org.publicwhip/lords/2022-02-10b.1924.0" newgid="uk.org.publicwhip/lords/2022-02-10c.1924.0" matchtype="perfectmatch"/>
<gidredirect oldgid="uk.org.publicwhip/lords/2022-02-10b.1924.1" newgid="uk.org.publicwhip/lords/2022-02-10c.1924.1" matchtype="perfectmatch"/>
<gidredirect oldgid="uk.org.publicwhip/lords/2022-02-10b.1924.2" newgid="uk.org.publicwhip/lords/2022-02-10c.1924.2" matchtype="perfectmatch"/>
<gidredirect oldgid="uk.org.publicwhip/lords/2022-02-10b.1924.3" newgid="uk.org.publicwhip/lords/2022-02-10c.1924.3" matchtype="perfectmatch"/>
<gidredirect oldgid="uk.org.publicwhip/lords/2022-02-10b.1924.4" newgid="uk.org.publicwhip/lords/2022-02-10c.1924.4" matchtype="perfectmatch"/>
<gidredirect oldgid="uk.org.publicwhip/lords/2022-02-10b.1925.0" newgid="uk.org.publicwhip/lords/2022-02-10c.1925.0" matchtype="perfectmatch"/>
<gidredirect oldgid="uk.org.publicwhip/lords/2022-02-10b.1925.1" newgid="uk.org.publicwhip/lords/2022-02-10c.1925.1" matchtype="perfectmatch"/>
<gidredirect oldgid="uk.org.publicwhip/lords/2022-02-10b.1925.2" newgid="uk.org.publicwhip/lords/2022-02-10c.1925.2" matchtype="perfectmatch"/>
<gidredirect oldgid="uk.org.publicwhip/lords/2022-02-10b.1925.3" newgid="uk.org.publicwhip/lords/2022-02-10c.1925.3" matchtype="perfectmatch"/>
<gidredirect oldgid="uk.org.publicwhip/lords/2022-02-10b.1925.4" newgid="uk.org.publicwhip/lords/2022-02-10c.1925.4" matchtype="perfectmatch"/>
<gidredirect oldgid="uk.org.publicwhip/lords/2022-02-10b.1926.0" newgid="uk.org.publicwhip/lords/2022-02-10c.1926.0" matchtype="perfectmatch"/>
<gidredirect oldgid="uk.org.publicwhip/lords/2022-02-10b.1928.0" newgid="uk.org.publicwhip/lords/2022-02-10c.1928.0" matchtype="perfectmatch"/>
<gidredirect oldgid="uk.org.publicwhip/lords/2022-02-10b.1929.0" newgid="uk.org.publicwhip/lords/2022-02-10c.1929.0" matchtype="perfectmatch"/>
<gidredirect oldgid="uk.org.publicwhip/lords/2022-02-10b.1930.0" newgid="uk.org.publicwhip/lords/2022-02-10c.1930.0" matchtype="perfectmatch"/>
<gidredirect oldgid="uk.org.publicwhip/lords/2022-02-10b.1931.0" newgid="uk.org.publicwhip/lords/2022-02-10c.1931.0" matchtype="perfectmatch"/>
<gidredirect oldgid="uk.org.publicwhip/lords/2022-02-10b.1931.1" newgid="uk.org.publicwhip/lords/2022-02-10c.1931.1" matchtype="perfectmatch"/>
<gidredirect oldgid="uk.org.publicwhip/lords/2022-02-10b.1932.0" newgid="uk.org.publicwhip/lords/2022-02-10c.1932.0" matchtype="perfectmatch"/>
<gidredirect oldgid="uk.org.publicwhip/lords/2022-02-10b.1932.1" newgid="uk.org.publicwhip/lords/2022-02-10c.1932.1" matchtype="perfectmatch"/>
<gidredirect oldgid="uk.org.publicwhip/lords/2022-02-10b.1933.0" newgid="uk.org.publicwhip/lords/2022-02-10c.1933.0" matchtype="perfectmatch"/>
<gidredirect oldgid="uk.org.publicwhip/lords/2022-02-10b.1934.0" newgid="uk.org.publicwhip/lords/2022-02-10c.1934.0" matchtype="perfectmatch"/>
<gidredirect oldgid="uk.org.publicwhip/lords/2022-02-10b.1934.1" newgid="uk.org.publicwhip/lords/2022-02-10c.1934.1" matchtype="perfectmatch"/>
<gidredirect oldgid="uk.org.publicwhip/lords/2022-02-10b.1935.0" newgid="uk.org.publicwhip/lords/2022-02-10c.1935.0" matchtype="perfectmatch"/>
<gidredirect oldgid="uk.org.publicwhip/lords/2022-02-10b.1935.1" newgid="uk.org.publicwhip/lords/2022-02-10c.1935.1" matchtype="perfectmatch"/>
<gidredirect oldgid="uk.org.publicwhip/lords/2022-02-10b.1935.2" newgid="uk.org.publicwhip/lords/2022-02-10c.1935.2" matchtype="perfectmatch"/>
<gidredirect oldgid="uk.org.publicwhip/lords/2022-02-10b.1936.0" newgid="uk.org.publicwhip/lords/2022-02-10c.1936.0" matchtype="perfectmatch"/>
<gidredirect oldgid="uk.org.publicwhip/lords/2022-02-10b.1937.0" newgid="uk.org.publicwhip/lords/2022-02-10c.1937.0" matchtype="perfectmatch"/>
<gidredirect oldgid="uk.org.publicwhip/lords/2022-02-10b.1937.1" newgid="uk.org.publicwhip/lords/2022-02-10c.1937.1" matchtype="perfectmatch"/>
<gidredirect oldgid="uk.org.publicwhip/lords/2022-02-10b.1937.2" newgid="uk.org.publicwhip/lords/2022-02-10c.1937.2" matchtype="perfectmatch"/>
<gidredirect oldgid="uk.org.publicwhip/lords/2022-02-10b.1938.0" newgid="uk.org.publicwhip/lords/2022-02-10c.1938.0" matchtype="perfectmatch"/>
<gidredirect oldgid="uk.org.publicwhip/lords/2022-02-10b.1938.1" newgid="uk.org.publicwhip/lords/2022-02-10c.1938.1" matchtype="perfectmatch"/>
<gidredirect oldgid="uk.org.publicwhip/lords/2022-02-10b.1938.2" newgid="uk.org.publicwhip/lords/2022-02-10c.1938.2" matchtype="perfectmatch"/>
<gidredirect oldgid="uk.org.publicwhip/lords/2022-02-10b.1938.3" newgid="uk.org.publicwhip/lords/2022-02-10c.1938.3" matchtype="perfectmatch"/>
<gidredirect oldgid="uk.org.publicwhip/lords/2022-02-10b.1939.0" newgid="uk.org.publicwhip/lords/2022-02-10c.1939.0" matchtype="perfectmatch"/>
<gidredirect oldgid="uk.org.publicwhip/lords/2022-02-10b.1940.0" newgid="uk.org.publicwhip/lords/2022-02-10c.1940.0" matchtype="perfectmatch"/>
<gidredirect oldgid="uk.org.publicwhip/lords/2022-02-10b.1940.1" newgid="uk.org.publicwhip/lords/2022-02-10c.1940.1" matchtype="perfectmatch"/>
<gidredirect oldgid="uk.org.publicwhip/lords/2022-02-10b.1940.2" newgid="uk.org.publicwhip/lords/2022-02-10c.1940.2" matchtype="perfectmatch"/>
<gidredirect oldgid="uk.org.publicwhip/lords/2022-02-10b.1940.3" newgid="uk.org.publicwhip/lords/2022-02-10c.1940.3" matchtype="perfectmatch"/>
<gidredirect oldgid="uk.org.publicwhip/lords/2022-02-10b.1940.4" newgid="uk.org.publicwhip/lords/2022-02-10c.1940.4" matchtype="perfectmatch"/>
<gidredirect oldgid="uk.org.publicwhip/lords/2022-02-10b.1943.0" newgid="uk.org.publicwhip/lords/2022-02-10c.1943.0" matchtype="perfectmatch"/>
<gidredirect oldgid="uk.org.publicwhip/lords/2022-02-10b.1944.0" newgid="uk.org.publicwhip/lords/2022-02-10c.1944.0" matchtype="perfectmatch"/>
<gidredirect oldgid="uk.org.publicwhip/lords/2022-02-10b.1944.1" newgid="uk.org.publicwhip/lords/2022-02-10c.1944.1" matchtype="perfectmatch"/>
<gidredirect oldgid="uk.org.publicwhip/lords/2022-02-10b.1944.2" newgid="uk.org.publicwhip/lords/2022-02-10c.1944.2" matchtype="perfectmatch"/>
<gidredirect oldgid="uk.org.publicwhip/lords/2022-02-10b.1944.3" newgid="uk.org.publicwhip/lords/2022-02-10c.1944.3" matchtype="perfectmatch"/>
<gidredirect oldgid="uk.org.publicwhip/lords/2022-02-10b.1945.0" newgid="uk.org.publicwhip/lords/2022-02-10c.1945.0" matchtype="perfectmatch"/>
<gidredirect oldgid="uk.org.publicwhip/lords/2022-02-10b.1945.1" newgid="uk.org.publicwhip/lords/2022-02-10c.1945.1" matchtype="perfectmatch"/>
<gidredirect oldgid="uk.org.publicwhip/lords/2022-02-10b.1945.2" newgid="uk.org.publicwhip/lords/2022-02-10c.1945.2" matchtype="perfectmatch"/>
<gidredirect oldgid="uk.org.publicwhip/lords/2022-02-10b.1945.3" newgid="uk.org.publicwhip/lords/2022-02-10c.1945.3" matchtype="perfectmatch"/>
<gidredirect oldgid="uk.org.publicwhip/lords/2022-02-10b.1946.0" newgid="uk.org.publicwhip/lords/2022-02-10c.1946.0" matchtype="perfectmatch"/>
<gidredirect oldgid="uk.org.publicwhip/lords/2022-02-10b.1946.1" newgid="uk.org.publicwhip/lords/2022-02-10c.1946.1" matchtype="perfectmatch"/>
<gidredirect oldgid="uk.org.publicwhip/lords/2022-02-10b.1947.0" newgid="uk.org.publicwhip/lords/2022-02-10c.1947.0" matchtype="perfectmatch"/>
<gidredirect oldgid="uk.org.publicwhip/lords/2022-02-10b.1948.0" newgid="uk.org.publicwhip/lords/2022-02-10c.1948.0" matchtype="perfectmatch"/>
<gidredirect oldgid="uk.org.publicwhip/lords/2022-02-10b.1949.0" newgid="uk.org.publicwhip/lords/2022-02-10c.1949.0" matchtype="perfectmatch"/>
<gidredirect oldgid="uk.org.publicwhip/lords/2022-02-10b.1949.1" newgid="uk.org.publicwhip/lords/2022-02-10c.1949.1" matchtype="perfectmatch"/>
<gidredirect oldgid="uk.org.publicwhip/lords/2022-02-10b.1949.2" newgid="uk.org.publicwhip/lords/2022-02-10c.1949.2" matchtype="perfectmatch"/>
<gidredirect oldgid="uk.org.publicwhip/lords/2022-02-10b.1949.3" newgid="uk.org.publicwhip/lords/2022-02-10c.1949.3" matchtype="perfectmatch"/>
<gidredirect oldgid="uk.org.publicwhip/lords/2022-02-10b.1949.4" newgid="uk.org.publicwhip/lords/2022-02-10c.1949.4" matchtype="perfectmatch"/>
<gidredirect oldgid="uk.org.publicwhip/lords/2022-02-10b.1949.5" newgid="uk.org.publicwhip/lords/2022-02-10c.1949.5" matchtype="perfectmatch"/>
<gidredirect oldgid="uk.org.publicwhip/lords/2022-02-10b.1950.0" newgid="uk.org.publicwhip/lords/2022-02-10c.1950.0" matchtype="perfectmatch"/>
<gidredirect oldgid="uk.org.publicwhip/lords/2022-02-10b.1950.1" newgid="uk.org.publicwhip/lords/2022-02-10c.1950.1" matchtype="perfectmatch"/>
<gidredirect oldgid="uk.org.publicwhip/lords/2022-02-10b.1951.0" newgid="uk.org.publicwhip/lords/2022-02-10c.1951.0" matchtype="perfectmatch"/>
<gidredirect oldgid="uk.org.publicwhip/lords/2022-02-10b.1951.1" newgid="uk.org.publicwhip/lords/2022-02-10c.1951.1" matchtype="perfectmatch"/>
<gidredirect oldgid="uk.org.publicwhip/lords/2022-02-10b.1951.2" newgid="uk.org.publicwhip/lords/2022-02-10c.1951.2" matchtype="perfectmatch"/>
<gidredirect oldgid="uk.org.publicwhip/lords/2022-02-10b.1951.3" newgid="uk.org.publicwhip/lords/2022-02-10c.1951.3" matchtype="perfectmatch"/>
<gidredirect oldgid="uk.org.publicwhip/lords/2022-02-10b.1951.4" newgid="uk.org.publicwhip/lords/2022-02-10c.1951.4" matchtype="perfectmatch"/>
<gidredirect oldgid="uk.org.publicwhip/lords/2022-02-10b.1952.0" newgid="uk.org.publicwhip/lords/2022-02-10c.1952.0" matchtype="perfectmatch"/>
<gidredirect oldgid="uk.org.publicwhip/lords/2022-02-10b.1952.1" newgid="uk.org.publicwhip/lords/2022-02-10c.1952.1" matchtype="perfectmatch"/>
<gidredirect oldgid="uk.org.publicwhip/lords/2022-02-10b.1953.0" newgid="uk.org.publicwhip/lords/2022-02-10c.1953.0" matchtype="perfectmatch"/>
<gidredirect oldgid="uk.org.publicwhip/lords/2022-02-10b.1954.0" newgid="uk.org.publicwhip/lords/2022-02-10c.1954.0" matchtype="perfectmatch"/>
<gidredirect oldgid="uk.org.publicwhip/lords/2022-02-10b.1955.0" newgid="uk.org.publicwhip/lords/2022-02-10c.1955.0" matchtype="perfectmatch"/>
<gidredirect oldgid="uk.org.publicwhip/lords/2022-02-10b.1956.0" newgid="uk.org.publicwhip/lords/2022-02-10c.1956.0" matchtype="perfectmatch"/>
<gidredirect oldgid="uk.org.publicwhip/lords/2022-02-10b.1958.0" newgid="uk.org.publicwhip/lords/2022-02-10c.1958.0" matchtype="perfectmatch"/>
<gidredirect oldgid="uk.org.publicwhip/lords/2022-02-10b.1958.1" newgid="uk.org.publicwhip/lords/2022-02-10c.1958.1" matchtype="perfectmatch"/>
<gidredirect oldgid="uk.org.publicwhip/lords/2022-02-10b.1959.0" newgid="uk.org.publicwhip/lords/2022-02-10c.1959.0" matchtype="perfectmatch"/>
<gidredirect oldgid="uk.org.publicwhip/lords/2022-02-10b.1960.0" newgid="uk.org.publicwhip/lords/2022-02-10c.1960.0" matchtype="perfectmatch"/>
<gidredirect oldgid="uk.org.publicwhip/lords/2022-02-10b.1960.1" newgid="uk.org.publicwhip/lords/2022-02-10c.1960.1" matchtype="perfectmatch"/>
<gidredirect oldgid="uk.org.publicwhip/lords/2022-02-10b.1960.2" newgid="uk.org.publicwhip/lords/2022-02-10c.1960.2" matchtype="perfectmatch"/>
<gidredirect oldgid="uk.org.publicwhip/lords/2022-02-10b.1961.0" newgid="uk.org.publicwhip/lords/2022-02-10c.1961.0" matchtype="perfectmatch"/>
<gidredirect oldgid="uk.org.publicwhip/lords/2022-02-10b.1962.0" newgid="uk.org.publicwhip/lords/2022-02-10c.1962.0" matchtype="perfectmatch"/>
<gidredirect oldgid="uk.org.publicwhip/lords/2022-02-10b.1962.1" newgid="uk.org.publicwhip/lords/2022-02-10c.1962.1" matchtype="perfectmatch"/>
<gidredirect oldgid="uk.org.publicwhip/lords/2022-02-10b.1963.0" newgid="uk.org.publicwhip/lords/2022-02-10c.1963.0" matchtype="perfectmatch"/>
<gidredirect oldgid="uk.org.publicwhip/lords/2022-02-10b.1964.0" newgid="uk.org.publicwhip/lords/2022-02-10c.1964.0" matchtype="perfectmatch"/>
<gidredirect oldgid="uk.org.publicwhip/lords/2022-02-10b.1964.1" newgid="uk.org.publicwhip/lords/2022-02-10c.1964.1" matchtype="perfectmatch"/>
<gidredirect oldgid="uk.org.publicwhip/lords/2022-02-10b.1966.0" newgid="uk.org.publicwhip/lords/2022-02-10c.1966.0" matchtype="perfectmatch"/>
<gidredirect oldgid="uk.org.publicwhip/lords/2022-02-10b.1967.0" newgid="uk.org.publicwhip/lords/2022-02-10c.1967.0" matchtype="perfectmatch"/>
<gidredirect oldgid="uk.org.publicwhip/lords/2022-02-10b.1967.1" newgid="uk.org.publicwhip/lords/2022-02-10c.1967.1" matchtype="perfectmatch"/>
<gidredirect oldgid="uk.org.publicwhip/lords/2022-02-10b.1968.0" newgid="uk.org.publicwhip/lords/2022-02-10c.1968.0" matchtype="perfectmatch"/>
<gidredirect oldgid="uk.org.publicwhip/lords/2022-02-10b.1968.1" newgid="uk.org.publicwhip/lords/2022-02-10c.1968.1" matchtype="perfectmatch"/>
<gidredirect oldgid="uk.org.publicwhip/lords/2022-02-10b.1968.2" newgid="uk.org.publicwhip/lords/2022-02-10c.1968.2" matchtype="perfectmatch"/>
<gidredirect oldgid="uk.org.publicwhip/lords/2022-02-10b.1971.0" newgid="uk.org.publicwhip/lords/2022-02-10c.1971.0" matchtype="perfectmatch"/>
<gidredirect oldgid="uk.org.publicwhip/lords/2022-02-10b.1973.0" newgid="uk.org.publicwhip/lords/2022-02-10c.1973.0" matchtype="perfectmatch"/>
<gidredirect oldgid="uk.org.publicwhip/lords/2022-02-10b.1973.1" newgid="uk.org.publicwhip/lords/2022-02-10c.1973.1" matchtype="perfectmatch"/>
<gidredirect oldgid="uk.org.publicwhip/lords/2022-02-10b.1974.0" newgid="uk.org.publicwhip/lords/2022-02-10c.1974.0" matchtype="multiplecover"/>
<gidredirect oldgid="uk.org.publicwhip/lords/2022-02-10b.1974.0" newgid="uk.org.publicwhip/lords/2022-02-10c.1975.0" matchtype="multiplecover"/>
<speech id="uk.org.publicwhip/lords/2022-02-10b.1974.0" speakername="Lord Sharpe of Epsom" type="Start Speech" person_id="uk.org.publicwhip/person/25955" colnum="1974" time="21:30:00" url="">
    <p pid="b1974.0/1">My Lords, again, I thank all noble Lords who have participated in this debate, and I thank all noble Lords who signed this amendment. I understand that their concerns centre around the accessibility of the route for those who are too young to obtain BNO status in their own right and who no longer reside with their BNO parents, or those whose BNO parents do not wish to apply to the route. Although perhaps unintended, the clause would also enable unaccompanied children under the age of 18 to apply independently of their parentswhich obviously risks creating safeguarding and other concerns.</p>
    <p pid="b1974.0/2">The BNO route was designed bearing in mind the moral and historic obligations the UK has to those who elected to retain ties to the UK by obtaining BNO status and who wish to make the UK their home. The route already enables adult children born on or after <phrase class="date" code="2022-07-01">1 July</phrase> 1997 to apply with their families where they are part of the BNOs householdwhich I think answers the question of the noble Lord, Lord Rosserensuring that family units are not split up. This is a generous provisionbeing over 18, there adult children fall outside the UK immigration systems usual definition of a dependent child. Nevertheless, the provision recognises that, although they are too  young to have been eligible to obtain BNO status in their own right, they may still be able to form a household with their BNO parent.</p>
    <p pid="b1974.0/3">I am going to make a brief digression into the numbers of people who have already applied, and  so on. As of <phrase class="date" code="2022-09-30">30 September</phrase>, over 88,000 people had appliedstatus holders and their family memberssince <phrase class="date" code="2022-01-31">31 January</phrase>, and 76,000 applications had been granted. The net-positive impact to the Treasuryin answer to the comment about the Chancellor and how he should be pleased about thisis estimated to be between 2.4 billion and 2.9 billion over five years. With that in mind, I would perhaps ask my noble friend Lord Patten why we did not grant BNO status to everybody back in 1997, which many of us in Hong Kong at the time thought would have been a very good idea. In answer to the subsequent question asked by the noble Lord, Lord Rosser, that number of 300,000 is accurateI do not know, though, how many would apply under this particular amendment, but obviously we will do some work on that and come back to him.</p>
    <p pid="b1974.0/4">Those who are not eligible for the BNO route do have a number of other UK immigration routes available to them, and that includes student visas which are  up 5% compared with 2019of course, there may be a pandemic effect in that as well. The skilled worker route enables individuals to come to the UK in a wider range of professions and at a lower general salary threshold than in the pastalthough, again, the information I have suggests the vast majority are very well educated indeed, as my noble friend pointed out. The graduate route is open to sponsored international students who have successfully completed a degree at undergraduate level or above. We believe that those existing routes provide avenues for many Hong Kong nationals to come to the UK, and we expect some new routes that will be created next year to open up another pathway to young Hong Kong nationals.</p>
    <p pid="b1974.0/5">However, we have heard the concerns raised by noble Lords around the appropriateness of some of these other routes and are very sympathetic to the circumstances of children born on or after <phrase class="date" code="2022-07-01">1 July</phrase> 1997 with BNO parents. We are, therefore, looking at whether more can be done to support this cohort wishing to build a permanent life in the UK. I can assure your Lordships that we are considering the matter carefully. I hope it will cheer your Lordships upparticularly when it comes to matters of precise timingto hear that we hope to update the House by Report stage. In light of these assurances, I ask the noble Lord to withdraw the amendment.</p>
    <p pid="b1974.0/6">I was very struck by what the noble Lord said about the positive impact that people make, both in purely economic termsthose figures of 2.4 billion to 2.9 billion over five years to the Treasury are an amazing statementand in human terms as well. I certainly know this from having volunteered as a student, a long time ago, to teach English to Hong Kong children who had come to United Kingdom and seeing what happened to them in the next generation: they produced a lawyer, a doctor, a teacher and an entrepreneur and, in the next generation, a goddaughter of mine. These people bring real gifts to our society. I know your Lordships House shares that view.</p>
    <p pid="b1974.0/7">On the basis of everything we have heard, I thank all noble Lords who have participated in this debate, but I am sure the Committee will agree that hearing the noble Lord, Lord Patten, was deeply inspiring. Many people from outside this House will have heard this debate, as the noble Baroness, Lady Smith, said, and hopefully many people who still have access to such things as the internet in Hong Kong will have seen on our parliamentary channel what the noble Lord had to say, because I think it will give them a great deal of inspiration. On the basis of what the noble Lord, Lord Sharpe, said, I beg leave to withdraw my amendment</p>
</speech>
<gidredirect oldgid="uk.org.publicwhip/lords/2022-02-10b.1976.0" newgid="uk.org.publicwhip/lords/2022-02-10c.1976.0" matchtype="perfectmatch"/>
<gidredirect oldgid="uk.org.publicwhip/lords/2022-02-10b.1976.1" newgid="uk.org.publicwhip/lords/2022-02-10c.1976.1" matchtype="perfectmatch"/>
<gidredirect oldgid="uk.org.publicwhip/lords/2022-02-10b.1976.2" newgid="uk.org.publicwhip/lords/2022-02-10c.1976.2" matchtype="perfectmatch"/>
<gidredirect oldgid="uk.org.publicwhip/lords/2022-02-10b.1976.3" newgid="uk.org.publicwhip/lords/2022-02-10c.1976.3" matchtype="perfectmatch"/>
<gidredirect oldgid="uk.org.publicwhip/lords/2022-02-10b.1976.4" newgid="uk.org.publicwhip/lords/2022-02-10c.1976.4" matchtype="perfectmatch"/>
<gidredirect oldgid="uk.org.publicwhip/lords/2022-02-10b.1976.5" newgid="uk.org.publicwhip/lords/2022-02-10c.1976.5" matchtype="perfectmatch"/>
<gidredirect oldgid="uk.org.publicwhip/lords/2022-02-10b.1977.0" newgid="uk.org.publicwhip/lords/2022-02-10c.1977.0" matchtype="perfectmatch"/>
<gidredirect oldgid="uk.org.publicwhip/lords/2022-02-10b.1979.0" newgid="uk.org.publicwhip/lords/2022-02-10c.1979.0" matchtype="perfectmatch"/>
<gidredirect oldgid="uk.org.publicwhip/lords/2022-02-10b.1980.0" newgid="uk.org.publicwhip/lords/2022-02-10c.1980.0" matchtype="perfectmatch"/>
<gidredirect oldgid="uk.org.publicwhip/lords/2022-02-10b.1980.1" newgid="uk.org.publicwhip/lords/2022-02-10c.1980.1" matchtype="perfectmatch"/>
<gidredirect oldgid="uk.org.publicwhip/lords/2022-02-10b.1981.0" newgid="uk.org.publicwhip/lords/2022-02-10c.1981.0" matchtype="perfectmatch"/>
<gidredirect oldgid="uk.org.publicwhip/lords/2022-02-10b.1982.0" newgid="uk.org.publicwhip/lords/2022-02-10c.1982.0" matchtype="perfectmatch"/>
<gidredirect oldgid="uk.org.publicwhip/lords/2022-02-10b.1982.1" newgid="uk.org.publicwhip/lords/2022-02-10c.1982.1" matchtype="perfectmatch"/>
<gidredirect oldgid="uk.org.publicwhip/lords/2022-02-10b.1982.2" newgid="uk.org.publicwhip/lords/2022-02-10c.1982.2" matchtype="perfectmatch"/>
<gidredirect oldgid="uk.org.publicwhip/lords/2022-02-10b.1982.3" newgid="uk.org.publicwhip/lords/2022-02-10c.1982.3" matchtype="perfectmatch"/>
<gidredirect oldgid="uk.org.publicwhip/lords/2022-02-10b.1983.0" newgid="uk.org.publicwhip/lords/2022-02-10c.1983.0" matchtype="perfectmatch"/>
<gidredirect oldgid="uk.org.publicwhip/lords/2022-02-10b.1984.0" newgid="uk.org.publicwhip/lords/2022-02-10c.1984.0" matchtype="perfectmatch"/>
<gidredirect oldgid="uk.org.publicwhip/lords/2022-02-10b.1984.1" newgid="uk.org.publicwhip/lords/2022-02-10c.1984.1" matchtype="perfectmatch"/>
<gidredirect oldgid="uk.org.publicwhip/lords/2022-02-10b.1985.0" newgid="uk.org.publicwhip/lords/2022-02-10c.1985.0" matchtype="perfectmatch"/>
<gidredirect oldgid="uk.org.publicwhip/lords/2022-02-10b.1985.1" newgid="uk.org.publicwhip/lords/2022-02-10c.1985.1" matchtype="perfectmatch"/>
<gidredirect oldgid="uk.org.publicwhip/lords/2022-02-10b.1985.2" newgid="uk.org.publicwhip/lords/2022-02-10c.1985.2" matchtype="perfectmatch"/>
<gidredirect oldgid="uk.org.publicwhip/lords/2022-02-10b.1985.3" newgid="uk.org.publicwhip/lords/2022-02-10c.1985.3" matchtype="perfectmatch"/>
<gidredirect oldgid="uk.org.publicwhip/lords/2022-02-10b.1985.4" newgid="uk.org.publicwhip/lords/2022-02-10c.1985.4" matchtype="perfectmatch"/>
<gidredirect oldgid="uk.org.publicwhip/lords/2022-02-10b.1985.5" newgid="uk.org.publicwhip/lords/2022-02-10c.1985.5" matchtype="perfectmatch"/>
<gidredirect oldgid="uk.org.publicwhip/lords/2022-02-10b.1986.0" newgid="uk.org.publicwhip/lords/2022-02-10c.1986.0" matchtype="perfectmatch"/>
<gidredirect oldgid="uk.org.publicwhip/lords/2022-02-10b.1988.0" newgid="uk.org.publicwhip/lords/2022-02-10c.1988.0" matchtype="perfectmatch"/>
<gidredirect oldgid="uk.org.publicwhip/lords/2022-02-10b.1989.0" newgid="uk.org.publicwhip/lords/2022-02-10c.1989.0" matchtype="perfectmatch"/>
<gidredirect oldgid="uk.org.publicwhip/lords/2022-02-10b.1991.0" newgid="uk.org.publicwhip/lords/2022-02-10c.1991.0" matchtype="perfectmatch"/>
<gidredirect oldgid="uk.org.publicwhip/lords/2022-02-10b.1992.0" newgid="uk.org.publicwhip/lords/2022-02-10c.1992.0" matchtype="perfectmatch"/>
<gidredirect oldgid="uk.org.publicwhip/lords/2022-02-10b.1993.0" newgid="uk.org.publicwhip/lords/2022-02-10c.1993.0" matchtype="perfectmatch"/>
<gidredirect oldgid="uk.org.publicwhip/lords/2022-02-10b.1993.1" newgid="uk.org.publicwhip/lords/2022-02-10c.1993.1" matchtype="perfectmatch"/>
<gidredirect oldgid="uk.org.publicwhip/lords/2022-02-10b.1994.0" newgid="uk.org.publicwhip/lords/2022-02-10c.1994.0" matchtype="perfectmatch"/>
<gidredirect oldgid="uk.org.publicwhip/lords/2022-02-10b.1994.1" newgid="uk.org.publicwhip/lords/2022-02-10c.1994.1" matchtype="perfectmatch"/>
<gidredirect oldgid="uk.org.publicwhip/lords/2022-02-10b.1994.2" newgid="uk.org.publicwhip/lords/2022-02-10c.1994.2" matchtype="perfectmatch"/>
<gidredirect oldgid="uk.org.publicwhip/lords/2022-02-10b.1995.0" newgid="uk.org.publicwhip/lords/2022-02-10c.1995.0" matchtype="perfectmatch"/>
<gidredirect oldgid="uk.org.publicwhip/lords/2022-02-10b.1995.1" newgid="uk.org.publicwhip/lords/2022-02-10c.1995.1" matchtype="perfectmatch"/>
<gidredirect oldgid="uk.org.publicwhip/lords/2022-02-10b.1995.2" newgid="uk.org.publicwhip/lords/2022-02-10c.1995.2" matchtype="perfectmatch"/>
<gidredirect oldgid="uk.org.publicwhip/lords/2022-02-10b.1996.0" newgid="uk.org.publicwhip/lords/2022-02-10c.1996.0" matchtype="perfectmatch"/>
<gidredirect oldgid="uk.org.publicwhip/lords/2022-02-10b.1997.0" newgid="uk.org.publicwhip/lords/2022-02-10c.1997.0" matchtype="perfectmatch"/>
<gidredirect oldgid="uk.org.publicwhip/lords/2022-02-10b.1997.1" newgid="uk.org.publicwhip/lords/2022-02-10c.1997.1" matchtype="perfectmatch"/>
<gidredirect oldgid="uk.org.publicwhip/lords/2022-02-10b.1997.2" newgid="uk.org.publicwhip/lords/2022-02-10c.1997.2" matchtype="perfectmatch"/>
<gidredirect oldgid="uk.org.publicwhip/lords/2022-02-10b.1999.0" newgid="uk.org.publicwhip/lords/2022-02-10c.1999.0" matchtype="perfectmatch"/>
<gidredirect oldgid="uk.org.publicwhip/lords/2022-02-10b.1999.1" newgid="uk.org.publicwhip/lords/2022-02-10c.1999.1" matchtype="perfectmatch"/>
<gidredirect oldgid="uk.org.publicwhip/lords/2022-02-10b.2000.0" newgid="uk.org.publicwhip/lords/2022-02-10c.1999.2" matchtype="perfectmatch"/>
</publicwhip>

